README.rst
setup.py
luastyle/__init__.py
luastyle/__main__.py
luastyle/core.py
luastyle/indent.py
luastyle/rewriter.py
luastyle.egg-info/PKG-INFO
luastyle.egg-info/SOURCES.txt
luastyle.egg-info/dependency_links.txt
luastyle.egg-info/entry_points.txt
luastyle.egg-info/not-zip-safe
luastyle.egg-info/requires.txt
luastyle.egg-info/top_level.txt
luastyle/tests/__init__.py
luastyle/tests/test_indent_rule.py