Metadata-Version: 1.1
Name: luastyle
Version: 1.2.3
Summary: A lua code formatter in Python !
Home-page: https://github.com/boolangery/py-lua-formatter
Author: Eliott Dumeix
Author-email: eliott.dumeix@gmail.com
License: MIT
Download-URL: https://github.com/boolangery/py-lua-style/archive/1.2.3.tar.gz
Platform: UNKNOWN
Classifier: Programming Language :: Python :: 3
Classifier: Programming Language :: Python :: 3.2
Classifier: Programming Language :: Python :: 3.3
Classifier: Programming Language :: Python :: 3.4
Classifier: Programming Language :: Python :: 3.5
Classifier: Programming Language :: Python :: 3.6
